LICENSE
README.md
patches/0002-feat-add-an-option-to-output-MD-in-the-XA-tag.patch
patches/0007-chore-use-htslib-s-kstring-when-available.patch
patches/0006-feat-try-to-speed-up-bam-record-creation.patch
patches/0003-feat-expose-various-internal-bwamem-methods-and-stru.patch
patches/0004-feat-add-mem_opt_print-for-debugging.patch
patches/0005-feat-adding-support-for-SAM-BAM-output-using-htslib.patch
patches/0001-feat-add-HN-tag-to-bwa-aln.patch
pybwa.libs/libgssapi_krb5-8fcd99a0.so.2.2
pybwa.libs/libk5crypto-2e098ed5.so.3.1
pybwa.libs/liblber-2-fc80a90f.4.so.2.10.9
pybwa.libs/liblzma-6f9d2abe.so.5.2.4
pybwa.libs/libbz2-549b318a.so.1.0.6
pybwa.libs/libnghttp2-3a94c239.so.14.17.0
pybwa.libs/libpcre2-8-8701a61e.so.0.7.1
pybwa.libs/libcrypt-258f54d5.so.1.1.0
pybwa.libs/libcrypto-3dc39733.so.1.1.1k
pybwa.libs/libbrotlicommon-b6e6c8bd.so.1.0.6
pybwa.libs/libkeyutils-fe6e95a9.so.1.6
pybwa.libs/libidn2-1b2a13b7.so.0.3.6
pybwa.libs/libunistring-be03fd41.so.2.1.0
pybwa.libs/libsasl2-076b3c1f.so.3.0.0
pybwa.libs/libkrb5-ce4232f2.so.3.3
pybwa.libs/libcurl-37295c13.so.4.5.0
pybwa.libs/libpsl-130094ea.so.5.3.1
pybwa.libs/libselinux-38862af2.so.1
pybwa.libs/libbrotlidec-5094ef0a.so.1.0.6
pybwa.libs/libkrb5support-2d7ea3a0.so.0.1
pybwa.libs/libcom_err-4a1178d7.so.2.1
pybwa.libs/libdeflate-1e665a73.so.0
pybwa.libs/libldap-2-28cb1a0e.4.so.2.10.9
pybwa.libs/libssh-5abd6818.so.4.8.7
pybwa.libs/libssl-b6e07dfa.so.1.1.1k
bwa/bwtgap.h
bwa/bwamem.c
bwa/bwtsw2_chain.c
bwa/bwtsw2.h
bwa/bwase.h
bwa/utils.h
bwa/bntseq.h
bwa/pemerge.c
bwa/kvec.h
bwa/kopen.c
bwa/example.c
bwa/malloc_wrap.h
bwa/neon_sse.h
bwa/khash.h
bwa/kthread.c
bwa/bwa.h
bwa/ksw.c
bwa/bntseq.c
bwa/bamlite.h
bwa/bwamem.h
bwa/bwt.c
bwa/bwtsw2_pair.c
bwa/bwashm.c
bwa/malloc_wrap.c
bwa/bwtsw2_aux.c
bwa/bwt.h
bwa/QSufSort.c
bwa/bwtaln.c
bwa/rope.c
bwa/Makefile
bwa/bwtsw2_main.c
bwa/bwase.c
bwa/fastmap.c
bwa/bwtindex.c
bwa/rle.h
bwa/scalar_sse.h
bwa/bwtgap.c
pybwa-2.1.0.dist-info/LICENSE
pybwa-2.1.0.dist-info/METADATA
pybwa-2.1.0.dist-info/WHEEL
pybwa-2.1.0.dist-info/RECORD
