Metadata-Version: 2.3
Name: pybwa
Version: 2.1.0
Summary: Python bindings for BWA
License: MIT
Keywords: bioinformatics
Author: Nils Homer
Author-email: nils@fulcrumgenomics.com
Requires-Python: >=3.9.0,<4.0
Classifier: Development Status :: 3 - Alpha
Classifier: Environment :: Console
Classifier: Intended Audience :: Developers
Classifier: Intended Audience :: Science/Research
Classifier: License :: OSI Approved :: MIT License
Classifier: Operating System :: OS Independent
Classifier: Programming Language :: Python :: 3
Classifier: Topic :: Scientific/Engineering :: Bio-Informatics
Classifier: Topic :: Software Development :: Documentation
Classifier: Topic :: Software Development :: Libraries :: Python Modules
Requires-Dist: fgpyo (>=0.7.0)
Requires-Dist: pysam (>=0.22.1)
Requires-Dist: typing_extensions (>=3.7.4) ; python_version < "3.13"
